pywinmm/__init__.py
pywinmm/pywinmm.py
pywinmm-0.3.dist-info/LICENSE.txt
pywinmm-0.3.dist-info/METADATA
pywinmm-0.3.dist-info/WHEEL
pywinmm-0.3.dist-info/top_level.txt
pywinmm-0.3.dist-info/RECORD
