Metadata-Version: 2.1
Name: pywinmm
Version: 0.3
Summary: a python library that works with win multy media dll
Home-page: https://github.com/baaziznasser/pywinmm
Download-URL: https://github.com/baaziznasser/pywinmm/archive/refs/tags/0.2.tar.gz
Author: nacer baaziz
Author-email: Nacer Baaziz <nacerbaaziz@ng-space.com>
License: GPL-3.0
Project-URL: Homepage, https://github.com/baaziznasser/pywinmm
Project-URL: Bug Tracker, https://github.com/baaziznasser/pywinmm/issues
Keywords: pywinmm,windows multy media,winmm.dll,pyaudio,mp3
Classifier: Development Status :: 5 - Production/Stable
Classifier: Intended Audience :: Developers
Classifier: Topic :: Software Development :: Build Tools
Classifier: Programming Language :: Python :: 3
Classifier: License :: OSI Approved :: GNU Affero General Public License v3 or later (AGPLv3+)
Classifier: Operating System :: Microsoft :: Windows
Requires-Python: >=3.4
License-File: LICENSE.txt
